bin_checker/__init__.py
bin_checker/bin_checker.py
pa_bin_checker-0.1.0.dist-info/LICENCE
pa_bin_checker-0.1.0.dist-info/METADATA
pa_bin_checker-0.1.0.dist-info/WHEEL
pa_bin_checker-0.1.0.dist-info/top_level.txt
pa_bin_checker-0.1.0.dist-info/RECORD
