Metadata-Version: 2.1
Name: pa-bin-checker
Version: 0.1.0
Summary: Python wrapper for Prompt API's BIN Checker API
Home-page: https://github.com/promptapi/bin-checker-py
Author: Prompt API
Author-email: hello@promptapi.com
License: MIT
Project-URL: Prompt API, https://promptapi.com
Project-URL: BIN Checker API, https://promptapi.com/marketplace/description/bincheck-api
Project-URL: Source, https://github.com/promptapi/bin-checker-py
Keywords: promptapi,bin,checker
Platform: UNKNOWN
Classifier: Development Status :: 5 - Production/Stable
Classifier: License :: OSI Approved :: MIT License
Classifier: Operating System :: OS Independent
Classifier: Programming Language :: Python :: 3
Classifier: Programming Language :: Python :: 3.7
Classifier: Programming Language :: Python :: 3 :: Only
Classifier: Intended Audience :: Developers
Classifier: Intended Audience :: Financial and Insurance Industry
Classifier: Topic :: Software Development :: Libraries :: Python Modules
Requires-Python: >=3.7
Requires-Dist: requests
Provides-Extra: development
Requires-Dist: vb-console ; extra == 'development'
